addbioschemas.py
addbioschemas-1.0.2.dist-info/METADATA
addbioschemas-1.0.2.dist-info/WHEEL
addbioschemas-1.0.2.dist-info/top_level.txt
addbioschemas-1.0.2.dist-info/RECORD
